LICENSE
MANIFEST.in
README.rst
setup.cfg
setup.py
sphinxleash/__init__.py
sphinxleash/helpers.py
sphinxleash/version.py
sphinxleash.egg-info/PKG-INFO
sphinxleash.egg-info/SOURCES.txt
sphinxleash.egg-info/dependency_links.txt
sphinxleash.egg-info/requires.txt
sphinxleash.egg-info/top_level.txt