Metadata-Version: 1.1
Name: sphinxleash
Version: 0.2.1
Summary: Lightweight framework for generating Sphinx docs
Home-page: none
Author: Ryan Dale
Author-email: dalerr@niddk.nih.gov
License: UNKNOWN
Platform: UNKNOWN
Classifier: Development Status :: 4 - Beta
Classifier: Intended Audience :: Science/Research
Classifier: Programming Language :: Python
Classifier: Programming Language :: Python :: 2
Classifier: Programming Language :: Python :: 2.6
Classifier: Programming Language :: Python :: 2.7
Classifier: Programming Language :: Python :: 3
Classifier: Programming Language :: Python :: 3.3
Classifier: License :: OSI Approved :: GNU General Public License (GPL)
